{
  "projectId": "gen-lang-client-0715548343",
  "appId": "1:211645716466:web:4b9e10d7d1dc8711ce7d6b",
  "apiKey": "AIzaSyA9GRpttRZlB331LjTTRQg61KneHWibAdg",
  "authDomain": "gen-lang-client-0715548343.firebaseapp.com",
  "firestoreDatabaseId": "ai-studio-jfcheck-ecf2c19f-8a9c-4b57-8025-a9ebdd99d347",
  "storageBucket": "gen-lang-client-0715548343.firebasestorage.app",
  "messagingSenderId": "211645716466",
  "measurementId": "",
  "oAuthClientId": "211645716466-pkbg08ss63doo2q2onm944r32tj2jftc.apps.googleusercontent.com",
  "recaptchaSiteKey": ""
}